[
    {
        "name": "Sea Beach",
        "price": "100.00",
        "description": "Tour means visit to a place or area, especially one during which you look around the place.",
        "img": "https://i.ibb.co/wgJSLfQ/01.png"
    },
    {
        "name": "Rice Terraces",
        "price": "120.00",
        "description": "Tour means visit to a place or area, especially one during which you look around the place.",
        "img": "https://i.ibb.co/m5LBKN6/02.png"
    },
    {
        "name": "Dark Forest",
        "price": "150.00",
        "description": "Tour means visit to a place or area, especially one during which you look around the place.",
        "img": "https://i.ibb.co/bRGbZ1m/03.png"
    },
    {
        "name": "Italy Tour",
        "price": "100.99",
        "description": "Tour means visit to a place or area, especially one during which you look around the place.",
        "img": "https://i.ibb.co/0Fr95pG/04.png"
    },
    {
        "name": "Hot Desert",
        "price": "299.00",
        "description": "Tour means visit to a place or area, especially one during which you look around the place.",
        "img": "https://i.ibb.co/7nCjggt/5.png"
    },
    {
        "name": "Peaceful Lake",
        "price": "299.00",
        "description": "Tour means visit to a place or area, especially one during which you look around the place.",
        "img": "https://i.ibb.co/1qvz0ng/06.png"
    },
    {
        "name": "Winter Tour",
        "price": "399.00",
        "description": "Tour means visit to a place or area, especially one during which you look around the place.",
        "img": "https://i.ibb.co/YXsfrjt/07.png"
    },
    {
        "name": "Mountain",
        "price": "299.00",
        "description": "Tour means visit to a place or area, especially one during which you look around the place.",
        "img": "https://i.ibb.co/R3kg77V/08.png"
    }
]